petsim/__init__.py
petsim/api/__init__.py
petsim/api/api/__init__.py
petsim/api/subclasses/__init__.py
petsim_py-1.1.4.dist-info/LICENSE
petsim_py-1.1.4.dist-info/METADATA
petsim_py-1.1.4.dist-info/WHEEL
petsim_py-1.1.4.dist-info/top_level.txt
petsim_py-1.1.4.dist-info/RECORD
