Metadata-Version: 2.1
Name: petsim-py
Version: 1.1.4
Summary: Wrapper for the BIG Games API.
Home-page: https://github.com/YbicG/petsim-py
Author: YbicG.Database
Author-email: YbicG <contact@ybicg.com>
Project-URL: Homepage, https://github.com/YbicG/petsim-py
Project-URL: Issues, https://github.com/YbicG/petsim-py/issues
Classifier: Programming Language :: Python :: 3
Classifier: License :: OSI Approved :: MIT License
Classifier: Operating System :: OS Independent
Requires-Python: >=3.8
License-File: LICENSE
